CHANGES.txt
COPYRIGHT.txt
LICENSE.txt
README.txt
bootstrap.py
pypi_upload.sh
setup.cfg
setup.py
collective/__init__.py
collective.cas4plone.egg-info/PKG-INFO
collective.cas4plone.egg-info/SOURCES.txt
collective.cas4plone.egg-info/dependency_links.txt
collective.cas4plone.egg-info/entry_points.txt
collective.cas4plone.egg-info/namespace_packages.txt
collective.cas4plone.egg-info/not-zip-safe
collective.cas4plone.egg-info/requires.txt
collective.cas4plone.egg-info/top_level.txt
collective/cas4plone/CASAuthHelper.py
collective/cas4plone/CASXMLResponseParser.py
collective/cas4plone/__init__.py
collective/cas4plone/configure.zcml
collective/cas4plone/zmi/CASAuthHelper.gif
collective/cas4plone/zmi/addCASAuthHelperForm.zpt