Metadata-Version: 1.0
Name: collective.cas4plone
Version: 1.0a2
Summary: A PAS plugin that authenticates users against a CAS (Central Authentication Service) server.
Home-page: UNKNOWN
Author: Timo Stollenwerk
Author-email: timo@zmag.de
License: ZPL
Keywords: zope PAS
Platform: UNKNOWN
Classifier: Framework :: Zope2
Classifier: Programming Language :: Python
Classifier: Topic :: Software Development :: Libraries :: Python Modules
